{
  "generated_at": "2026-06-29T09:23:10Z",
  "source": "/home/statpan/workspace/opensource/datapan-registry/reports/epost-verification.json",
  "provider": "data.go.kr",
  "registry": "/home/statpan/workspace/opensource/datapan-registry/.datapan/data-go-kr.registry.json",
  "limit": 20,
  "truncated": false,
  "summary": {
    "total": 18,
    "verified": 0,
    "failed": 0,
    "skipped": 18,
    "unknown": 0
  },
  "groups": {
    "by_status": [
      {
        "key": "skipped",
        "count": 18,
        "status": "skipped"
      }
    ],
    "by_reason": [
      {
        "key": "epost_wadl_metadata_only",
        "count": 12,
        "reason": "epost_wadl_metadata_only"
      },
      {
        "key": "epost_missing_required_params",
        "count": 2,
        "reason": "epost_missing_required_params"
      },
      {
        "key": "epost_unsupported_protocol",
        "count": 2,
        "reason": "epost_unsupported_protocol"
      },
      {
        "key": "missing_auth",
        "count": 2,
        "reason": "missing_auth"
      }
    ],
    "by_provider": [
      {
        "key": "epost",
        "count": 18,
        "provider": "epost"
      }
    ],
    "by_endpoint_host": [
      {
        "key": "openapi.epost.go.kr:80",
        "count": 14,
        "host": "openapi.epost.go.kr:80"
      },
      {
        "key": "openapi.epost.go.kr",
        "count": 4,
        "host": "openapi.epost.go.kr"
      }
    ],
    "by_kind": [
      {
        "key": "external_endpoint",
        "count": 18,
        "kind": "external_endpoint"
      }
    ]
  }
}
