{
  "generated_at": "2026-06-25T03:05:54Z",
  "source": "C:\\workspace\\datapan-registry\\reports\\latest-verification.json",
  "provider": "data.go.kr",
  "registry": "C:\\workspace\\datapan-registry\\data\\data-go-kr.registry.json",
  "limit": 0,
  "truncated": false,
  "summary": {
    "total": 238,
    "verified": 21,
    "failed": 78,
    "skipped": 139,
    "unknown": 0
  },
  "groups": {
    "by_status": [
      {
        "key": "skipped",
        "count": 139,
        "status": "skipped"
      },
      {
        "key": "failed",
        "count": 78,
        "status": "failed"
      },
      {
        "key": "verified",
        "count": 21,
        "status": "verified"
      }
    ],
    "by_reason": [
      {
        "key": "approval_required",
        "count": 26,
        "reason": "approval_required"
      },
      {
        "key": "tour_service_root_missing_operation_path",
        "count": 19,
        "reason": "tour_service_root_missing_operation_path"
      },
      {
        "key": "oneclick_connection_refused",
        "count": 11,
        "reason": "oneclick_connection_refused"
      },
      {
        "key": "andong_service_not_registered",
        "count": 10,
        "reason": "andong_service_not_registered"
      },
      {
        "key": "missing_required_params",
        "count": 10,
        "reason": "missing_required_params"
      },
      {
        "key": "sisul_wadl_metadata_only",
        "count": 10,
        "reason": "sisul_wadl_metadata_only"
      },
      {
        "key": "qnet_wadl_metadata_only",
        "count": 9,
        "reason": "qnet_wadl_metadata_only"
      },
      {
        "key": "epost_wadl_metadata_only",
        "count": 8,
        "reason": "epost_wadl_metadata_only"
      },
      {
        "key": "korad_wadl_metadata_only",
        "count": 8,
        "reason": "korad_wadl_metadata_only"
      },
      {
        "key": "naqs_mutation_endpoint",
        "count": 8,
        "reason": "naqs_mutation_endpoint"
      },
      {
        "key": "ekape_missing_required_params",
        "count": 7,
        "reason": "ekape_missing_required_params"
      },
      {
        "key": "humetro_service_access_denied",
        "count": 7,
        "reason": "humetro_service_access_denied"
      },
      {
        "key": "tour_service_key_not_registered",
        "count": 7,
        "reason": "tour_service_key_not_registered"
      },
      {
        "key": "itfind_missing_required_params",
        "count": 6,
        "reason": "itfind_missing_required_params"
      },
      {
        "key": "sisul_request_timeout",
        "count": 6,
        "reason": "sisul_request_timeout"
      },
      {
        "key": "uiryeong_service_key_not_registered",
        "count": 6,
        "reason": "uiryeong_service_key_not_registered"
      },
      {
        "key": "andong_missing_required_params",
        "count": 5,
        "reason": "andong_missing_required_params"
      },
      {
        "key": "epost_unsupported_protocol",
        "count": 5,
        "reason": "epost_unsupported_protocol"
      },
      {
        "key": "lh_ebid_service_key_not_registered",
        "count": 5,
        "reason": "lh_ebid_service_key_not_registered"
      },
      {
        "key": "airport_service_key_not_registered",
        "count": 4,
        "reason": "airport_service_key_not_registered"
      },
      {
        "key": "ekape_service_key_not_registered",
        "count": 4,
        "reason": "ekape_service_key_not_registered"
      },
      {
        "key": "geoje_missing_required_params",
        "count": 4,
        "reason": "geoje_missing_required_params"
      },
      {
        "key": "seoul_bus_service_key_not_registered",
        "count": 4,
        "reason": "seoul_bus_service_key_not_registered"
      },
      {
        "key": "itfind_endpoint_not_found",
        "count": 3,
        "reason": "itfind_endpoint_not_found"
      },
      {
        "key": "jeonju_http_404_not_found",
        "count": 3,
        "reason": "jeonju_http_404_not_found"
      },
      {
        "key": "sisul_missing_required_params",
        "count": 3,
        "reason": "sisul_missing_required_params"
      },
      {
        "key": "ulsan_missing_required_params",
        "count": 3,
        "reason": "ulsan_missing_required_params"
      },
      {
        "key": "ulsan_service_key_not_registered",
        "count": 3,
        "reason": "ulsan_service_key_not_registered"
      },
      {
        "key": "airport_missing_required_params",
        "count": 2,
        "reason": "airport_missing_required_params"
      },
      {
        "key": "epost_missing_required_params",
        "count": 2,
        "reason": "epost_missing_required_params"
      },
      {
        "key": "jeonju_http_405_method_not_allowed",
        "count": 2,
        "reason": "jeonju_http_405_method_not_allowed"
      },
      {
        "key": "ekape_html_response",
        "count": 1,
        "reason": "ekape_html_response"
      },
      {
        "key": "folk_missing_required_params",
        "count": 1,
        "reason": "folk_missing_required_params"
      },
      {
        "key": "humetro_deadline_expired",
        "count": 1,
        "reason": "humetro_deadline_expired"
      },
      {
        "key": "lh_ebid_missing_required_params",
        "count": 1,
        "reason": "lh_ebid_missing_required_params"
      },
      {
        "key": "oneclick_missing_required_params",
        "count": 1,
        "reason": "oneclick_missing_required_params"
      },
      {
        "key": "qnet_connection_validation_failed",
        "count": 1,
        "reason": "qnet_connection_validation_failed"
      },
      {
        "key": "seoul_bus_missing_required_params",
        "count": 1,
        "reason": "seoul_bus_missing_required_params"
      }
    ],
    "by_provider": [
      {
        "key": "oneclick-law",
        "count": 30,
        "provider": "oneclick-law"
      },
      {
        "key": "tour",
        "count": 26,
        "provider": "tour"
      },
      {
        "key": "sisul",
        "count": 20,
        "provider": "sisul"
      },
      {
        "key": "andong",
        "count": 15,
        "provider": "andong"
      },
      {
        "key": "ekape",
        "count": 15,
        "provider": "ekape"
      },
      {
        "key": "epost",
        "count": 15,
        "provider": "epost"
      },
      {
        "key": "korad",
        "count": 15,
        "provider": "korad"
      },
      {
        "key": "q-net",
        "count": 15,
        "provider": "q-net"
      },
      {
        "key": "itfind",
        "count": 13,
        "provider": "itfind"
      },
      {
        "key": "data.go.kr",
        "count": 10,
        "provider": "data.go.kr"
      },
      {
        "key": "naqs",
        "count": 9,
        "provider": "naqs"
      },
      {
        "key": "humetro",
        "count": 8,
        "provider": "humetro"
      },
      {
        "key": "airport",
        "count": 6,
        "provider": "airport"
      },
      {
        "key": "geoje",
        "count": 6,
        "provider": "geoje"
      },
      {
        "key": "lh-ebid",
        "count": 6,
        "provider": "lh-ebid"
      },
      {
        "key": "uiryeong",
        "count": 6,
        "provider": "uiryeong"
      },
      {
        "key": "ulsan",
        "count": 6,
        "provider": "ulsan"
      },
      {
        "key": "jeonju",
        "count": 5,
        "provider": "jeonju"
      },
      {
        "key": "seoul-bus",
        "count": 5,
        "provider": "seoul-bus"
      },
      {
        "key": "forest",
        "count": 4,
        "provider": "forest"
      },
      {
        "key": "folk",
        "count": 3,
        "provider": "folk"
      }
    ],
    "by_endpoint_host": [
      {
        "key": "oneclick.law.go.kr:80",
        "count": 27,
        "host": "oneclick.law.go.kr:80"
      },
      {
        "key": "data.sisul.or.kr",
        "count": 20,
        "host": "data.sisul.or.kr"
      },
      {
        "key": "data.ekape.or.kr",
        "count": 15,
        "host": "data.ekape.or.kr"
      },
      {
        "key": "openapi.q-net.or.kr",
        "count": 15,
        "host": "openapi.q-net.or.kr"
      },
      {
        "key": "www.andong.go.kr",
        "count": 15,
        "host": "www.andong.go.kr"
      },
      {
        "key": "www.korad.or.kr",
        "count": 15,
        "host": "www.korad.or.kr"
      },
      {
        "key": "open.itfind.or.kr",
        "count": 13,
        "host": "open.itfind.or.kr"
      },
      {
        "key": "openapi.epost.go.kr:80",
        "count": 13,
        "host": "openapi.epost.go.kr:80"
      },
      {
        "key": "apis.data.go.kr",
        "count": 10,
        "host": "apis.data.go.kr"
      },
      {
        "key": "data.naqs.go.kr",
        "count": 9,
        "host": "data.naqs.go.kr"
      },
      {
        "key": "data.humetro.busan.kr",
        "count": 8,
        "host": "data.humetro.busan.kr"
      },
      {
        "key": "openapi.tour.go.kr",
        "count": 7,
        "host": "openapi.tour.go.kr"
      },
      {
        "key": "data.geoje.go.kr",
        "count": 6,
        "host": "data.geoje.go.kr"
      },
      {
        "key": "data.uiryeong.go.kr",
        "count": 6,
        "host": "data.uiryeong.go.kr"
      },
      {
        "key": "openapi.airport.co.kr",
        "count": 6,
        "host": "openapi.airport.co.kr"
      },
      {
        "key": "openapi.ebid.lh.or.kr",
        "count": 6,
        "host": "openapi.ebid.lh.or.kr"
      },
      {
        "key": "openapi.its.ulsan.kr",
        "count": 6,
        "host": "openapi.its.ulsan.kr"
      },
      {
        "key": "openapi.jeonju.go.kr",
        "count": 5,
        "host": "openapi.jeonju.go.kr"
      },
      {
        "key": "ws.bus.go.kr",
        "count": 5,
        "host": "ws.bus.go.kr"
      },
      {
        "key": "api.forest.go.kr",
        "count": 4,
        "host": "api.forest.go.kr"
      },
      {
        "key": "folkency.nfm.go.kr",
        "count": 3,
        "host": "folkency.nfm.go.kr"
      },
      {
        "key": "oneclick.law.go.kr",
        "count": 3,
        "host": "oneclick.law.go.kr"
      },
      {
        "key": "openapi.epost.go.kr",
        "count": 2,
        "host": "openapi.epost.go.kr"
      }
    ],
    "by_kind": [
      {
        "key": "external_endpoint",
        "count": 209,
        "kind": "external_endpoint"
      },
      {
        "key": "service_root",
        "count": 19,
        "kind": "service_root"
      },
      {
        "key": "data_go_kr_gateway",
        "count": 10,
        "kind": "data_go_kr_gateway"
      }
    ]
  }
}
